emsg/__init__.py
emsg/box/__init__.py
emsg/box/emsg_box.py
emsg/box/full_box.py
emsg/box/id3v2/__init__.py
emsg/cli/__init__.py
emsg/cli/emsg.py
emsg-0.0.4.dist-info/LICENSE
emsg-0.0.4.dist-info/METADATA
emsg-0.0.4.dist-info/WHEEL
emsg-0.0.4.dist-info/entry_points.txt
emsg-0.0.4.dist-info/top_level.txt
emsg-0.0.4.dist-info/RECORD
