Metadata-Version: 2.1
Name: emsg
Version: 0.0.4
Summary: An ISO BMFF emsg atom generator
Home-page: https://github.com/ygoto3/emsg
Author: ygoto3
Author-email: my.important.apes@gmail.com
License: UNKNOWN
Project-URL: Bug Reports, https://github.com/ygoto3/emsg/issues
Project-URL: Source, https://github.com/ygoto3/emsg
Platform: UNKNOWN
Classifier: Development Status :: 3 - Alpha
Classifier: Intended Audience :: Developers
Classifier: License :: OSI Approved :: MIT License
Classifier: Operating System :: POSIX :: Linux
Classifier: Operating System :: MacOS :: MacOS X
Classifier: Operating System :: Microsoft :: Windows
Classifier: Programming Language :: Python :: 3.7
Classifier: Programming Language :: Python :: 3.10
Classifier: Programming Language :: Python :: 3 :: Only
